nlp_exp/__init__.py
nlp_exp/operations.py
numpy_nlp_lab_1-0.1.dist-info/METADATA
numpy_nlp_lab_1-0.1.dist-info/WHEEL
numpy_nlp_lab_1-0.1.dist-info/top_level.txt
numpy_nlp_lab_1-0.1.dist-info/RECORD
