Metadata-Version: 2.1
Name: numpy-nlp-lab-1
Version: 0.1
Summary: A custom NLP package
Author: Your Name
